configtree/__init__.py
configtree/formatter.py
configtree/loader.py
configtree/script.py
configtree/source.py
configtree/tree.py
configtree/compat/__init__.py
configtree/compat/colabc.py
configtree/compat/types.py
ConfigTree-0.6.dist-info/LICENSE.txt
ConfigTree-0.6.dist-info/METADATA
ConfigTree-0.6.dist-info/WHEEL
ConfigTree-0.6.dist-info/entry_points.txt
ConfigTree-0.6.dist-info/top_level.txt
ConfigTree-0.6.dist-info/zip-safe
ConfigTree-0.6.dist-info/RECORD
