Metadata-Version: 2.1
Name: ConfigTree
Version: 0.6
Summary: Is a configuration management tool
Home-page: https://github.com/Cottonwood-Technology/ConfigTree
Author: Cottonwood Technology
Author-email: info@cottonwood.tech
License: BSD
Keywords: configuration config settings tree
Platform: UNKNOWN
Classifier: License :: OSI Approved :: BSD License
Classifier: Programming Language :: Python
Classifier: Programming Language :: Python :: 2.7
Classifier: Programming Language :: Python :: 3.5
Classifier: Programming Language :: Python :: 3.6
Classifier: Programming Language :: Python :: 3.7
Classifier: Programming Language :: Python :: 3.8
Classifier: Programming Language :: Python :: Implementation :: CPython
Classifier: Programming Language :: Python :: Implementation :: PyPy
Classifier: Topic :: Software Development :: Libraries :: Python Modules
Classifier: Intended Audience :: Developers
Classifier: Intended Audience :: System Administrators
Requires-Dist: pyyaml
Requires-Dist: cached-property
